qthandy/__init__.py
qthandy/filter.py
qthandy/layout.py
test/__init__.py
test/common.py
test/test_basic.py
test/test_filter.py
test/test_font.py
test/test_layout.py
test/test_widgets.py
qt_handy-0.4.0.dist-info/LICENSE
qt_handy-0.4.0.dist-info/METADATA
qt_handy-0.4.0.dist-info/WHEEL
qt_handy-0.4.0.dist-info/top_level.txt
qt_handy-0.4.0.dist-info/RECORD
