Metadata-Version: 2.1
Name: qt-handy
Version: 0.4.0
Summary: A collection of useful Qt utilities and event filters for PyQt/PySide
Home-page: https://github.com/plotlyst/qt-handy
Author: Zsolt Kovari
Author-email: zsolt@kovaridev.com
Classifier: Programming Language :: Python :: 3
Classifier: Operating System :: OS Independent
Requires-Python: >=3.7, <4
License-File: LICENSE
Requires-Dist: qtpy
Provides-Extra: all
Requires-Dist: qtpy ; extra == 'all'
Requires-Dist: pytest ; extra == 'all'
Requires-Dist: pytest-qt ; extra == 'all'
Requires-Dist: pytest-cov ; extra == 'all'
Requires-Dist: pytest-randomly ; extra == 'all'
Provides-Extra: core
Requires-Dist: qtpy ; extra == 'core'
Provides-Extra: dev
Requires-Dist: pytest ; extra == 'dev'
Requires-Dist: pytest-qt ; extra == 'dev'
Requires-Dist: pytest-cov ; extra == 'dev'
Requires-Dist: pytest-randomly ; extra == 'dev'
Provides-Extra: doc
Provides-Extra: test
Requires-Dist: pytest ; extra == 'test'
Requires-Dist: pytest-qt ; extra == 'test'
Requires-Dist: pytest-cov ; extra == 'test'
Requires-Dist: pytest-randomly ; extra == 'test'
